gorunpy/__init__.py
gorunpy/cli.py
gorunpy-0.6.0.dist-info/METADATA
gorunpy-0.6.0.dist-info/WHEEL
gorunpy-0.6.0.dist-info/entry_points.txt
gorunpy-0.6.0.dist-info/top_level.txt
gorunpy-0.6.0.dist-info/RECORD
