Metadata-Version: 2.4
Name: gorunpy
Version: 0.6.0
Summary: Python SDK for Go-callable executables
Requires-Python: >=3.9
Provides-Extra: build
Requires-Dist: pyinstaller>=6.0.0; extra == "build"
